NotiMe/NotiMe.py
NotiMe/__init__.py
NotiMe/__main__.py
NotiMe-0.0.2.dist-info/LICENSE
NotiMe-0.0.2.dist-info/METADATA
NotiMe-0.0.2.dist-info/WHEEL
NotiMe-0.0.2.dist-info/entry_points.txt
NotiMe-0.0.2.dist-info/top_level.txt
NotiMe-0.0.2.dist-info/RECORD
