Metadata-Version: 2.1
Name: NotiMe
Version: 0.0.2
Summary: A simple notification program
Home-page: https://github.com/pruet/notime
Author: Pruet Boonma
Author-email: pruetboonma@gmail.com
License: MIT
Platform: UNKNOWN
Classifier: Programming Language :: Python :: 3
Classifier: License :: OSI Approved :: MIT License
Classifier: Operating System :: OS Independent
Requires-Python: >=3.6
License-File: LICENSE
Requires-Dist: requests (~=2.27)
Requires-Dist: argparse (~=1.4)
Requires-Dist: configparser (~=5.2)
